excel_db_connector/__init__.py
excel_db_connector/excel.py
excel_db_connector-0.3.0.dist-info/LICENSE
excel_db_connector-0.3.0.dist-info/METADATA
excel_db_connector-0.3.0.dist-info/WHEEL
excel_db_connector-0.3.0.dist-info/top_level.txt
excel_db_connector-0.3.0.dist-info/RECORD
